lm_deezer_bf_dec-0.0.1b4.dist-info/METADATA
lm_deezer_bf_dec-0.0.1b4.dist-info/WHEEL
lm_deezer_bf_dec/__init__.py
lm_deezer_bf_dec/__init__.pyi
lm_deezer_bf_dec/py.typed
lm_deezer_bf_dec/lm_deezer_bf_dec.cp38-win32.pyd
lm_deezer_bf_dec-0.0.1b4.dist-info/RECORD
