Metadata-Version: 2.1
Name: lm_deezer_bf_dec
Version: 0.0.1b4
Classifier: Programming Language :: Rust
Classifier: Programming Language :: Python :: Implementation :: CPython
Classifier: Programming Language :: Python :: Implementation :: PyPy
Classifier: Development Status :: 4 - Beta
Summary: A simple RUST package with scope to speed up the blowfish decryption process for deezer tracks.
Author-email: An0nimia <an0nimia@protonmail.com>
Requires-Python: >=3.8
Project-URL: Homepage, https://github.com/an0nimia/lm_deezer_bf_dec
Project-URL: Bug Tracker, https://github.com/an0nimia/lm_deezer_bf_dec/issues
